table_nan_val/__init__.py
table_nan_val/table_nan_val.py
table_nan_val-1.0.0.dist-info/LICENSE
table_nan_val-1.0.0.dist-info/METADATA
table_nan_val-1.0.0.dist-info/WHEEL
table_nan_val-1.0.0.dist-info/top_level.txt
table_nan_val-1.0.0.dist-info/RECORD
