Metadata-Version: 2.1
Name: table-nan-val
Version: 1.0.0
Summary: find missing value for DataFrame
Home-page: https://github.com/bdfd/6.1-PyPI_Table_Nan_Val
Author: BDFD
Author-email: bdfd2005@gmail.com
License: UNKNOWN
Project-URL: Bug Tracker, https://github.com/bdfd/6.1-PyPI_Table_Nan_Val/issues
Platform: UNKNOWN
Classifier: Programming Language :: Python :: 3
Classifier: License :: OSI Approved :: MIT License
Classifier: Operating System :: OS Independent
Requires-Python: >=3.6
License-File: LICENSE
Requires-Dist: numpy (>=1.19.5)
Requires-Dist: pandas (>=1.1.5)
Requires-Dist: matplotlib (>=3.2.2)
